{"inkVersion":21,"root":[["\n",{"->":"greeting"},["done",{"#f":5,"#n":"g-0"}],null],"done",{"greeting":[["#","^portrait: npc_default ","/#","#","^speaker: generic NPC ","/#","#","^layout: left ","/#","#","^audio: aris1","/#","^\"Greetings traveler.\"","\n","ev","str","^Ask about location","/str","/ev",{"*":".^.c-0","flg":4},"ev","str","^Request help","/str","/ev",{"*":".^.c-1","flg":4},"ev","str","^Leave","/str","/ev",{"*":".^.c-2","flg":4},{"c-0":["^ ","\n","^\"This is a place of business.\"","\n","end",{"#f":5}],"c-1":["\n","^\"I'm afraid I can't help with that right now.\"","\n","end",{"#f":5}],"c-2":["\n","^\"Safe journeys.\"","\n","end",{"#f":5}]}],{"#f":1}],"idle":["#","^portrait: npc_default ","/#","#","^speaker: Quest Giver 1 ","/#","#","^layout: left ","/#","#","^audio: aris1","/#","^\"Is there something else you needed?\"","\n",{"->":"greeting"},{"#f":1}],"farewell":["#","^portrait: npc_default ","/#","#","^speaker: Quest Giver 1 ","/#","#","^layout: left ","/#","#","^audio: aris1","/#","^\"Come back anytime.\"","\n","end",{"#f":1}],"global decl":["ev","str","^","/str",{"VAR=":"player_name"},"str","^REQUIREMENTS_NOT_MET","/str",{"VAR=":"CollectCoinsQuest"},"str","^REQUIREMENTS_NOT_MET","/str",{"VAR=":"VisitBoxesQuest"},"/ev","end",null],"#f":1}],"listDefs":{}}